pzmolib/__init__.py
pzmolib/appliances_clear.py
pzmolib/banking_features.py
pzmolib/beauty_efficiency.py
pzmolib/caesarean_features.py
pzmolib/ckdisease_efficiency.py
pzmolib/customer_clear.py
pzmolib/financial_clear.py
pzmolib/financial_features.py
pzmolib/forest_clear.py
pzmolib/glass_optimization.py
pzmolib/income_optimization.py
pzmolib/kidney_clear.py
pzmolib/loan_clear.py
pzmolib/marrket_efficiency.py
pzmolib/mushroom_features.py
pzmolib/mushroom_optimization.py
pzmolib/star_cat_visualisation.py
pzmolib/star_optimization.py
pzmolib/yeh_clear.py
pzmolib-0.1.0.dist-info/WHEEL
pzmolib-0.1.0.dist-info/entry_points.txt
pzmolib-0.1.0.dist-info/METADATA
pzmolib-0.1.0.dist-info/RECORD
