Metadata-Version: 2.3
Name: pzmolib
Version: 0.1.0
Summary: Add your description here
Author: DaSh-More
Author-email: DaSh-More <danila-763@yandex.ru>
Requires-Dist: pyperclip>=1.11.0
Requires-Python: >=3.12
